pyflvmeta/__init__.py
pyflvmeta/flvmeta
pyflvmeta/flvmeta.exe
pyflvmeta/wrapper.py
py_flvmeta-0.0.2.dist-info/LICENSE
py_flvmeta-0.0.2.dist-info/METADATA
py_flvmeta-0.0.2.dist-info/WHEEL
py_flvmeta-0.0.2.dist-info/top_level.txt
py_flvmeta-0.0.2.dist-info/RECORD
