Metadata-Version: 2.1
Name: py-flvmeta
Version: 0.0.2
Summary: A Python wraper for flvmeta
Author: qqyuanxinqq
License: GNU GENERAL PUBLIC LICENSE
Project-URL: Homepage, https://github.com/qqyuanxinqq/py-flvmeta
Project-URL: Bug Tracker, https://github.com/qqyuanxinqq/py-flvmeta/issues
Classifier: Programming Language :: Python :: 3
Classifier: License :: OSI Approved :: GNU General Public License v2 (GPLv2)
Classifier: Operating System :: OS Independent
Requires-Python: >=3.7
License-File: LICENSE
